miepython/__init__.py
miepython/bessel.py
miepython/core.py
miepython/field.py
miepython/mie_jit.py
miepython/mie_nojit.py
miepython/monte_carlo.py
miepython/rayleigh.py
miepython/util.py
miepython/vsh.py
miepython/data/Johnson.txt
miepython/data/ag-Johnson.txt
miepython/data/segelstein81_index.txt
miepython/examples/01_dielectric.py
miepython/examples/02_glass.py
miepython/examples/03_droplets.py
miepython/examples/04_gold.py
miepython-3.0.2.dist-info/licenses/LICENSE.txt
miepython-3.0.2.dist-info/METADATA
miepython-3.0.2.dist-info/WHEEL
miepython-3.0.2.dist-info/top_level.txt
miepython-3.0.2.dist-info/RECORD
