Metadata-Version: 2.4
Name: miepython
Version: 3.0.2
Summary: Mie scattering of a plane wave by a sphere
Home-page: https://github.com/scottprahl/miepython.git
Author: Scott Prahl
Author-email: scott.prahl@oit.edu
License: MIT License
Keywords: mie,scattering,rainbow,droplet,backscatter,sphere,nanoparticle,cloud,phase function,efficiency,rayleigh,backscattering
Classifier: Development Status :: 5 - Production/Stable
Classifier: License :: OSI Approved :: MIT License
Classifier: Intended Audience :: Science/Research
Classifier: Programming Language :: Python
Classifier: Programming Language :: Python :: 3
Classifier: Programming Language :: Python :: 3.8
Classifier: Programming Language :: Python :: 3.9
Classifier: Programming Language :: Python :: 3.10
Classifier: Programming Language :: Python :: 3.11
Classifier: Programming Language :: Python :: 3.12
Requires-Python: >=3.8
License-File: LICENSE.txt
Requires-Dist: numpy
Requires-Dist: matplotlib
Requires-Dist: numba
Requires-Dist: scipy
Dynamic: author
Dynamic: author-email
Dynamic: home-page
Dynamic: license-file
